pipestream/__init__.py
pipestream/pipeline.py
pipestream-1.0.1.dist-info/LICENSE
pipestream-1.0.1.dist-info/METADATA
pipestream-1.0.1.dist-info/WHEEL
pipestream-1.0.1.dist-info/top_level.txt
pipestream-1.0.1.dist-info/RECORD
