Metadata-Version: 2.1
Name: pipestream
Version: 1.0.1
Summary: A convenient way to 'pipe' a given input through a series of classes or callables
Author-email: Rafael Acioly <aciolyr@gmail.com>
Project-URL: Homepage, https://github.com/rafa-acioly/pipestream
Project-URL: Bug Tracker, https://github.com/rafa-acioly/pipestream/issues
Keywords: pipeline,middleware
Classifier: Programming Language :: Python :: 3
Classifier: License :: OSI Approved :: MIT License
Classifier: Operating System :: OS Independent
Requires-Python: >=3.10
License-File: LICENSE
